setup.py
ssa_cme_one/__init__.py
ssa_cme_one/ssa_1.py
ssa_solve_cme.egg-info/PKG-INFO
ssa_solve_cme.egg-info/SOURCES.txt
ssa_solve_cme.egg-info/dependency_links.txt
ssa_solve_cme.egg-info/top_level.txt