Metadata-Version: 2.1
Name: ssa-solve-cme
Version: 0.0.1
Summary: this is a new method called ‘ssa’ which used to solve CME
Home-page: https://github.com
Author: roy_fan
License: UNKNOWN
Platform: UNKNOWN
Classifier: Programming Language :: Python :: 3
Classifier: License :: OSI Approved :: MIT License
Classifier: Operating System :: OS Independent
